datasette_pretty_traces/__init__.py
datasette_pretty_traces/static/datasette-pretty-traces.js
datasette_pretty_traces-0.6.dist-info/licenses/LICENSE
datasette_pretty_traces-0.6.dist-info/METADATA
datasette_pretty_traces-0.6.dist-info/WHEEL
datasette_pretty_traces-0.6.dist-info/entry_points.txt
datasette_pretty_traces-0.6.dist-info/top_level.txt
datasette_pretty_traces-0.6.dist-info/RECORD
