Metadata-Version: 2.4
Name: datasette-pretty-traces
Version: 0.6
Summary: Prettier formatting for ?_trace=1 traces
Author: Simon Willison
License-Expression: Apache-2.0
Project-URL: Homepage, https://github.com/simonw/datasette-pretty-traces
Project-URL: Changelog, https://github.com/simonw/datasette-pretty-traces/releases
Project-URL: Issues, https://github.com/simonw/datasette-pretty-traces/issues
Project-URL: CI, https://github.com/simonw/datasette-pretty-traces/actions
Classifier: Framework :: Datasette
Requires-Python: >=3.10
License-File: LICENSE
Requires-Dist: datasette
Provides-Extra: test
Requires-Dist: pytest; extra == "test"
Requires-Dist: pytest-asyncio; extra == "test"
Dynamic: license-file
